[{"backPort":3306,"deptName":"天门市recall","backUserName":"root","mainPassword":"123456","backIpAddress":"localhost","mainPort":3306,"mainIpAddress":"localhost","mainUserName":"root","id":1,"backDatabaseName":"recall2","backPassword":"123456","mainDatabaseName":"recall"},{"backPort":3306,"deptName":"天门市公共资源","backUserName":"root","mainPassword":"123456","backIpAddress":"192.168.2.123","mainPort":3306,"mainIpAddress":"192.168.2.123","mainUserName":"root","id":2,"backDatabaseName":"tmsggzy-front","backPassword":"123456","mainDatabaseName":"tmsggzy-core"},{"backPort":3306,"deptName":"天门市工商局","backUserName":"root","mainPassword":"123456","backIpAddress":"127.0.0.1","mainPort":3306,"mainIpAddress":"127.0.0.1","mainUserName":"root","id":3,"backDatabaseName":"tmsgsj2","backPassword":"123456","mainDatabaseName":"tmsgsj"}]